pylops/__init__.py
pylops/_torchoperator.py
pylops/config.py
pylops/jaxoperator.py
pylops/linearoperator.py
pylops/pytensoroperator.py
pylops/torchoperator.py
pylops/version.py
pylops/avo/__init__.py
pylops/avo/avo.py
pylops/avo/poststack.py
pylops/avo/prestack.py
pylops/basicoperators/__init__.py
pylops/basicoperators/_spread_numba.py
pylops/basicoperators/block.py
pylops/basicoperators/blockdiag.py
pylops/basicoperators/causalintegration.py
pylops/basicoperators/conj.py
pylops/basicoperators/diagonal.py
pylops/basicoperators/directionalderivative.py
pylops/basicoperators/firstderivative.py
pylops/basicoperators/flip.py
pylops/basicoperators/functionoperator.py
pylops/basicoperators/gradient.py
pylops/basicoperators/hstack.py
pylops/basicoperators/identity.py
pylops/basicoperators/imag.py
pylops/basicoperators/kronecker.py
pylops/basicoperators/laplacian.py
pylops/basicoperators/linearregression.py
pylops/basicoperators/matrixmult.py
pylops/basicoperators/memoizeoperator.py
pylops/basicoperators/pad.py
pylops/basicoperators/real.py
pylops/basicoperators/regression.py
pylops/basicoperators/restriction.py
pylops/basicoperators/roll.py
pylops/basicoperators/secondderivative.py
pylops/basicoperators/smoothing1d.py
pylops/basicoperators/smoothing2d.py
pylops/basicoperators/spread.py
pylops/basicoperators/sum.py
pylops/basicoperators/symmetrize.py
pylops/basicoperators/tocupy.py
pylops/basicoperators/transpose.py
pylops/basicoperators/vstack.py
pylops/basicoperators/zero.py
pylops/optimization/__init__.py
pylops/optimization/basesolver.py
pylops/optimization/basic.py
pylops/optimization/callback.py
pylops/optimization/cls_basic.py
pylops/optimization/cls_leastsquares.py
pylops/optimization/cls_sparsity.py
pylops/optimization/eigs.py
pylops/optimization/leastsquares.py
pylops/optimization/sparsity.py
pylops/signalprocessing/__init__.py
pylops/signalprocessing/_baseffts.py
pylops/signalprocessing/_chirpradon2d.py
pylops/signalprocessing/_chirpradon3d.py
pylops-2.4.0.dist-info/LICENSE.md
pylops-2.4.0.dist-info/METADATA
pylops-2.4.0.dist-info/WHEEL
pylops-2.4.0.dist-info/top_level.txt
pylops-2.4.0.dist-info/RECORD
