Metadata-Version: 2.1
Name: pylops
Version: 2.4.0
Summary: Python library implementing linear operators to allow solving large-scale optimization problems
Author-email: Matteo Ravasi <matteoravasi@gmail.com>
License:                    GNU LESSER GENERAL PUBLIC LICENSE
Keywords: algebra,inverse problems,large-scale optimization
Classifier: Development Status :: 5 - Production/Stable
Classifier: Intended Audience :: Developers
Classifier: Intended Audience :: Science/Research
Classifier: Intended Audience :: Education
Classifier: License :: OSI Approved :: GNU Lesser General Public License v3 (LGPLv3)
Classifier: Natural Language :: English
Classifier: Operating System :: OS Independent
Classifier: Programming Language :: Python :: 3 :: Only
Classifier: Programming Language :: Python :: 3.8
Classifier: Programming Language :: Python :: 3.9
Classifier: Programming Language :: Python :: 3.10
Classifier: Topic :: Scientific/Engineering :: Mathematics
License-File: LICENSE.md
Requires-Dist: numpy>=1.21.0
Requires-Dist: scipy>=1.11.0
Provides-Extra: advanced
Requires-Dist: llvmlite; extra == "advanced"
Requires-Dist: numba; extra == "advanced"
Requires-Dist: pyfftw; extra == "advanced"
Requires-Dist: PyWavelets; extra == "advanced"
Requires-Dist: scikit-fmm; extra == "advanced"
Requires-Dist: spgl1; extra == "advanced"
Requires-Dist: dtcwt; extra == "advanced"
